moonchart/__init__.py
moonchart/_version.py
moonchart/base.py
moonchart/exceptions.py
moonchart/paramscan.py
moonchart/perf.py
moonchart/py.typed
moonchart/shortfall.py
moonchart/tearsheet.py
moonchart/utils.py
moonchart/_tests/__init__.py
moonchart/_tests/test_perf.py
moonchart/_tests/test_utils.py
quantrocket_moonchart-2.10.0.0.dist-info/LICENSE.txt
quantrocket_moonchart-2.10.0.0.dist-info/METADATA
quantrocket_moonchart-2.10.0.0.dist-info/WHEEL
quantrocket_moonchart-2.10.0.0.dist-info/top_level.txt
quantrocket_moonchart-2.10.0.0.dist-info/RECORD
