Metadata-Version: 2.1
Name: quantrocket-moonchart
Version: 2.10.0.0
Summary: Moonchart
Home-page: https://www.quantrocket.com
Author: QuantRocket LLC
Author-email: support@quantrocket.com
License: Apache-2.0
License-File: LICENSE.txt
Requires-Dist: matplotlib
Requires-Dist: pandas >=0.20
Requires-Dist: seaborn
Requires-Dist: quantrocket-client
Requires-Dist: empyrical
Requires-Dist: scipy
